stereo/__init__.py
stereo/common.py
stereo/constant.py
stereo/log_manager.py
stereo/stereo_config.py
stereo/algorithm/__init__.py
stereo/algorithm/_louvain.py
stereo/algorithm/algorithm_base.py
stereo/algorithm/algorithm_err_code.py
stereo/algorithm/cell_correction.py
stereo/algorithm/cell_correction_fast.py
stereo/algorithm/cell_correction_fast_by_mask.py
stereo/algorithm/co_occurrence.py
stereo/algorithm/community_detection.py
stereo/algorithm/dendrogram.py
stereo/algorithm/dim_reduce.py
stereo/algorithm/draw_contours.py
stereo/algorithm/gaussian_smooth.py
stereo/algorithm/gen_ccc_micro_envs.py
stereo/algorithm/gen_mesh.py
stereo/algorithm/get_niche.py
stereo/algorithm/highly_variable_genes.py
stereo/algorithm/leiden.py
stereo/algorithm/log1p_fake.py
stereo/algorithm/mannwhitneyu.py
stereo/algorithm/ms_algorithm_base.py
stereo/algorithm/ms_community_detection.py
stereo/algorithm/ms_log1p_fake.py
stereo/algorithm/ms_spa_track.py
stereo/algorithm/neighbors.py
stereo/algorithm/normalization.py
stereo/algorithm/paga.py
stereo/algorithm/phenograph.py
stereo/algorithm/scale.py
stereo/algorithm/scenic.py
stereo/algorithm/score_genes.py
stereo/algorithm/score_genes_cell_cycle.py
stereo/algorithm/spa_track.py
stereo/algorithm/spatial_hotspot.py
stereo/algorithm/spatial_pattern_score.py
stereo/algorithm/statistics.py
stereo/algorithm/time_series_analysis.py
stereo/algorithm/total_vi.py
stereo/algorithm/umap.py
stereo/algorithm/batch_qc/__init__.py
stereo/algorithm/batch_qc/batchqc_raw.py
stereo/algorithm/batch_qc/main.py
stereo/algorithm/batch_qc/module/__init__.py
stereo/algorithm/batch_qc/module/classifier.py
stereo/algorithm/batch_qc/module/dataset.py
stereo/algorithm/batch_qc/module/early_stop.py
stereo/algorithm/batch_qc/module/loss.py
stereo/algorithm/batch_qc/module/trainer.py
stereo/algorithm/batch_qc/score/__init__.py
stereo/algorithm/batch_qc/score/get_neighbors.py
stereo/algorithm/batch_qc/score/kbet.py
stereo/algorithm/batch_qc/score/ksim.py
stereopy-1.6.0.dist-info/LICENSE
stereopy-1.6.0.dist-info/METADATA
stereopy-1.6.0.dist-info/WHEEL
stereopy-1.6.0.dist-info/entry_points.txt
stereopy-1.6.0.dist-info/top_level.txt
stereopy-1.6.0.dist-info/RECORD
